{
  "required": true,
  "minVersion": "0.8",
  "package": "dev.hexnowloading.dungeonnowloading.mixin",
  "compatibilityLevel": "JAVA_21",
  "mixins": [
    "FireBlockAccessor",
    "block.MimiclingBlockSmeltTransformMixin",
    "block.MimiclingBlockDropsMixin",
    "block.MimiclingReachServerGameModeMixin",
    "inventory.AnvilMenuMixin",
    "entities.MimiclingLivingEntityMixin",
    "entities.MimiclingPlayerMixin",
    "entities.MimiclingReachServerPacketMixin",
    "items.ItemStackBreakProtectionMixin"
  ],
  "client": [
    "MixinMinecraft",
    "client.MimiclingReachGameRendererMixin"
  ],
  "server": [
  ],
  "injectors": {
    "defaultRequire": 1
  }
}
